LICENSE
MANIFEST.in
README.md
setup.py
sparseprop/__init__.py
sparseprop/backend.cpp
sparseprop/utils.py
sparseprop.egg-info/PKG-INFO
sparseprop.egg-info/SOURCES.txt
sparseprop.egg-info/dependency_links.txt
sparseprop.egg-info/requires.txt
sparseprop.egg-info/top_level.txt
sparseprop/lib/sparse_conv2d.cpp
sparseprop/lib/sparse_conv2d_over_on.cpp
sparseprop/lib/sparse_linear.cpp
sparseprop/lib/utils.cpp
sparseprop/modules/__init__.py
sparseprop/modules/conv2d.py
sparseprop/modules/functions.py
sparseprop/modules/linear.py
sparseprop/modules/utils.py